py_presentation_forum/Handle.py
py_presentation_forum/Route.py
py_presentation_forum/Utils.py
py_presentation_forum/__init__.py
py_presentation_foundation-1.0.1.dist-info/LICENSE
py_presentation_foundation-1.0.1.dist-info/METADATA
py_presentation_foundation-1.0.1.dist-info/WHEEL
py_presentation_foundation-1.0.1.dist-info/top_level.txt
py_presentation_foundation-1.0.1.dist-info/RECORD
