Metadata-Version: 2.1
Name: py-presentation-foundation
Version: 1.0.1
Summary: A html binding to Tkinter UI
Author: SharkooMaster (Ali Al Rashini)
Author-email: <info@techpology.com>
Keywords: python,tkinter,better ui,html python
Classifier: Development Status :: 1 - Planning
Classifier: Intended Audience :: Developers
Classifier: Programming Language :: Python :: 3
Classifier: Operating System :: Unix
Classifier: Operating System :: MacOS :: MacOS X
Classifier: Operating System :: Microsoft :: Windows
License-File: LICENSE
Requires-Dist: tkinterweb
